hubbledemo/__init__.py
hubbledemo/cli.py
hubbledemo/cloud.py
hubbledemo/elfmgr.py
pyhubbledemo-0.0.8.dist-info/METADATA
pyhubbledemo-0.0.8.dist-info/WHEEL
pyhubbledemo-0.0.8.dist-info/entry_points.txt
pyhubbledemo-0.0.8.dist-info/licenses/LICENSE
pyhubbledemo-0.0.8.dist-info/RECORD
