Metadata-Version: 2.4
Name: pyhubbledemo
Version: 0.0.8
Summary: Hubble demo functionality for flashing and provisioning boards
Author-email: Paul Buckley <paul@hubble.com>
License-Expression: Apache-2.0
License-File: LICENSE
Classifier: Operating System :: OS Independent
Classifier: Programming Language :: Python :: 3
Requires-Python: >=3.9
Requires-Dist: click
Requires-Dist: intelhex
Requires-Dist: petname
Requires-Dist: pyelftools
Requires-Dist: pyhubblenetwork
Requires-Dist: pylink-square
Requires-Dist: requests
